flask_sockets.py
py3socket-0.2.1.3.dist-info/LICENSE
py3socket-0.2.1.3.dist-info/METADATA
py3socket-0.2.1.3.dist-info/WHEEL
py3socket-0.2.1.3.dist-info/top_level.txt
py3socket-0.2.1.3.dist-info/RECORD
