Metadata-Version: 2.1
Name: py3socket
Version: 0.2.1.3
Summary: Elegant WebSockets for your Flask apps, revised for Python 3.
Home-page: https://github.com/ruqqus/flask-sockets
Author: Ruqqus LLC
Author-email: info@ruqqus.com
License: See License
Platform: any
Classifier: Environment :: Web Environment
Classifier: Intended Audience :: Developers
Classifier: License :: OSI Approved :: MIT License
Classifier: Operating System :: OS Independent
Classifier: Programming Language :: Python
Classifier: Topic :: Internet :: WWW/HTTP :: Dynamic Content
Classifier: Topic :: Software Development :: Libraries :: Python Modules
Requires-Dist: Flask
Requires-Dist: gevent
Requires-Dist: gevent-websocket
